{
  "dependencies": {
    "mssql1": {
      "ignored": "true",
      "type": "mssql",
      "connectionId": "ConnectionStrings:HotelContext"
    },
    "mssql2": {
      "ignored": "true",
      "type": "mssql",
      "connectionId": "ConnectionStrings:azure"
    },
    "mssql3": {
      "serviceConnectorResourceId": "/subscriptions/[parameters('subscriptionId')]/resourceGroups/[parameters('serviceConnectorResourceGroupName')]/providers/Microsoft.Web/sites/DAT154Hotel/providers/Microsoft.ServiceLinker/linkers/ConnectionStringsDatabaseConnection_23175EAB21",
      "secretStore": "AzureAppSettings",
      "resourceId": "/subscriptions/[parameters('subscriptionId')]/resourceGroups/[parameters('resourceGroupName')]/providers/Microsoft.Sql/servers/dat154hotel/databases/HotelDB",
      "type": "mssql.azure",
      "connectionId": "ConnectionStrings:DatabaseConnection"
    }
  }
}